odoo/addons/stock_release_channel_cutoff/README.rst
odoo/addons/stock_release_channel_cutoff/__init__.py
odoo/addons/stock_release_channel_cutoff/__manifest__.py
odoo/addons/stock_release_channel_cutoff/i18n/fr.po
odoo/addons/stock_release_channel_cutoff/i18n/it.po
odoo/addons/stock_release_channel_cutoff/i18n/stock_release_channel_cutoff.pot
odoo/addons/stock_release_channel_cutoff/models/__init__.py
odoo/addons/stock_release_channel_cutoff/models/stock_release_channel.py
odoo/addons/stock_release_channel_cutoff/readme/CONTRIBUTORS.md
odoo/addons/stock_release_channel_cutoff/readme/CREDITS.md
odoo/addons/stock_release_channel_cutoff/readme/DESCRIPTION.md
odoo/addons/stock_release_channel_cutoff/static/description/icon.png
odoo/addons/stock_release_channel_cutoff/static/description/index.html
odoo/addons/stock_release_channel_cutoff/tests/__init__.py
odoo/addons/stock_release_channel_cutoff/tests/test_compute_cutoff_time.py
odoo/addons/stock_release_channel_cutoff/views/stock_release_channel_views.xml
odoo_addon_stock_release_channel_cutoff-18.0.1.0.3.dist-info/METADATA
odoo_addon_stock_release_channel_cutoff-18.0.1.0.3.dist-info/WHEEL
odoo_addon_stock_release_channel_cutoff-18.0.1.0.3.dist-info/top_level.txt
odoo_addon_stock_release_channel_cutoff-18.0.1.0.3.dist-info/RECORD
