Metadata-Version: 2.1
Name: odoo-addon-stock_release_channel_cutoff
Version: 18.0.1.0.3
Requires-Python: >=3.10
Requires-Dist: odoo-addon-stock_release_channel==18.0.*
Requires-Dist: odoo-addon-stock_release_channel_process_end_time==18.0.*
Requires-Dist: odoo==18.0.*
Summary: Add the cutoff time to the release channel
Home-page: https://github.com/OCA/stock-logistics-release-channel
License: AGPL-3
Author: Camptocamp, BCIM, Odoo Community Association (OCA)
Author-email: support@odoo-community.org
Classifier: Programming Language :: Python
Classifier: Framework :: Odoo
Classifier: Framework :: Odoo :: 18.0
Classifier: License :: OSI Approved :: GNU Affero General Public License v3
